open_pinball_db/__init__.py
open_pinball_db/client.py
open_pinball_db/exceptions.py
open_pinball_db-0.1.0.dist-info/LICENSE
open_pinball_db-0.1.0.dist-info/METADATA
open_pinball_db-0.1.0.dist-info/WHEEL
open_pinball_db-0.1.0.dist-info/RECORD
