Metadata-Version: 2.1
Name: open-pinball-db
Version: 0.1.0
Summary: An open pinball database client for Python
Home-page: https://github.com/Mollemoll/open-pinball-db
License: MIT
Keywords: pinball,database,client
Author: Mollemoll
Author-email: jonas.molander@gmail.com
Requires-Python: >=3.9,<4.0
Classifier: Intended Audience :: Developers
Classifier: License :: OSI Approved :: MIT License
Classifier: Programming Language :: Python
Classifier: Programming Language :: Python :: 3
Classifier: Programming Language :: Python :: 3.9
Classifier: Programming Language :: Python :: 3.10
Classifier: Programming Language :: Python :: 3.11
Classifier: Programming Language :: Python :: 3.12
Classifier: Topic :: Software Development :: Libraries
Classifier: Topic :: Software Development :: Libraries :: Python Modules
Requires-Dist: requests (>=2.32.3,<3.0.0)
Project-URL: Documentation, https://github.com/Mollemoll/open-pinball-db#readme
Project-URL: Repository, https://github.com/Mollemoll/open-pinball-db
